sruntool/SrunEncrypt.py
sruntool/SrunOperator.py
sruntool/__init__.py
sruntool/ecode_explain.py
sruntool/exception.py
sruntool/utils.py
sruntool-0.1.0.dist-info/LICENSE
sruntool-0.1.0.dist-info/METADATA
sruntool-0.1.0.dist-info/WHEEL
sruntool-0.1.0.dist-info/top_level.txt
sruntool-0.1.0.dist-info/RECORD
