Metadata-Version: 2.1
Name: sruntool
Version: 0.1.0
Summary: A library that can operate srun network
Home-page: https://github.com/AkagiYui/srun_tool
Author: AkagiYui
Author-email: akagiyui@yeah.net
License: UNKNOWN
Platform: UNKNOWN
Classifier: Development Status :: 4 - Beta
Classifier: Programming Language :: Python :: 3.9
Classifier: Intended Audience :: Developers
Classifier: License :: OSI Approved :: MIT License
Classifier: Operating System :: OS Independent
Requires-Python: >=3.7
License-File: LICENSE
